LICENSE
MANIFEST.in
README.rst
setup.cfg
setup.py
rum_docs_theme/__init__.py
rum_docs_theme/layout.html
rum_docs_theme/theme.conf
rum_docs_theme.egg-info/PKG-INFO
rum_docs_theme.egg-info/SOURCES.txt
rum_docs_theme.egg-info/dependency_links.txt
rum_docs_theme.egg-info/entry_points.txt
rum_docs_theme.egg-info/top_level.txt
rum_docs_theme/static/copybutton.js
rum_docs_theme/static/rumdoctheme.css
rum_docs_theme/static/sidebar.js