Metadata-Version: 1.1
Name: rum-docs-theme
Version: 2020.6
Summary: The Sphinx theme for Rum docs and related projects
Home-page: https://rum-lang.github.io
Author: tasuka
Author-email: <t1ra@protonmail.com>
License: PSFL/MPL 2.0
Platform: UNKNOWN
Classifier: Intended Audience :: Developers
Classifier: License :: OSI Approved :: Mozilla Public License 2.0 (MPL 2.0)
Classifier: License :: OSI Approved :: Python Software Foundation License
Classifier: Operating System :: OS Independent
Classifier: Topic :: Documentation
Classifier: Topic :: Software Development :: Documentation
